{
	
	"preset-1" : {"image_size":"thumbnail","member_image_size":{"unit":"px","size":90,"sizes":[]},"social_icons_border_radius":{"unit":"%","top":"","right":"","bottom":"","left":"","isLinked":true},"icon_size":{"unit":"px","size":14,"sizes":[]},"icon_bg_size":{"unit":"px","size":25,"sizes":[]},"icon_spacing":{"unit":"px","size":8,"sizes":[]},"member_image_height":{"unit":"px","size":90,"sizes":[]},"separator_position":"below_name","separator_thickness":{"unit":"px","size":1,"sizes":[]},"image_shape":"circle","image_border":"solid","image_border_size":{"unit":"px","top":"3","right":"3","bottom":"3","left":"3","isLinked":true},"image_border_color":"#02010126","image_margin_bottom":{"unit":"px","size":10,"sizes":[]},"desc_margin":{"unit":"px","size":20,"sizes":[]},"_margin":{"unit":"px","top":"10","right":"10","bottom":"10","left":"10","isLinked":true},"_padding":{"unit":"px","top":"10","right":"10","bottom":"10","left":"10","isLinked":true},"separator_size":{"unit":"%","size":18,"sizes":[]},"shape":"circle","content_padding":{"unit":"px","top":"8","right":"8","bottom":"8","left":"8","isLinked":true},"name_margin":{"unit":"px","size":10,"sizes":[]},"separator_margin":{"unit":"px","size":10,"sizes":[]},"social_icons_settings":"yes","show_team_member_desig":"","separator_settings":"yes","_background_background":"","_background_color":"","_border_width":{"unit":"px","top":"","right":"","bottom":"","left":"","isLinked":true},"_border_border":"","show_team_member_desc":"yes"},
	
	
	"preset-2" : {"image_size":"large","member_image_size":{"unit":"px","size":120,"sizes":[]},"social_icons_border_radius":{"unit":"%","top":"","right":"","bottom":"","left":"","isLinked":true},"icon_size":{"unit":"px","size":16,"sizes":[]},"icon_bg_size":{"unit":"px","size":28,"sizes":[]},"icon_spacing":{"unit":"px","size":8,"sizes":[]},"member_image_height":{"unit":"px","size":120,"sizes":[]},"separator_position":"below_desig","separator_size":{"unit":"%","size":"","sizes":[]},"separator_thickness":{"unit":"px","size":1,"sizes":[]},"social_icons_settings":"","image_shape":"circle","image_border":"solid","image_border_size":{"unit":"px","top":"3","right":"3","bottom":"3","left":"3","isLinked":true},"image_border_color":"#02010126","name_size":"h4","image_margin_bottom":{"unit":"px","size":10,"sizes":[]},"desc_margin":{"unit":"px","size":18,"sizes":[]},"_margin":{"unit":"px","top":"10","right":"10","bottom":"10","left":"10","isLinked":true},"_padding":{"unit":"px","top":"10","right":"10","bottom":"10","left":"10","isLinked":true},"separator_settings":"","show_team_member_desc":"","show_team_member_desig":"yes","content_padding":{"unit":"px","top":"","right":"","bottom":"","left":"","isLinked":true},"name_margin":{"unit":"px","size":"","sizes":[]},"separator_margin":{"unit":"px","size":"","sizes":[]},"_background_background":"","_background_color":"","_border_width":{"unit":"px","top":"","right":"","bottom":"","left":"","isLinked":true},"_border_border":""},
	
	"preset-3" : {"image_size":"full","member_image_size":{"unit":"px","size":"","sizes":[]},"member_image_height":{"unit":"px","size":"","sizes":[]},"social_icons_border_radius":{"unit":"%","top":"","right":"","bottom":"","left":"","isLinked":true},"icon_size":{"unit":"px","size":14,"sizes":[]},"icon_bg_size":{"unit":"px","size":25,"sizes":[]},"icon_spacing":{"unit":"px","size":8,"sizes":[]},"separator_settings":"","separator_position":"below_desig","separator_size":{"unit":"%","size":10,"sizes":[]},"separator_thickness":{"unit":"px","size":1,"sizes":[]},"team_member_image_border_radius":{"unit":"%","top":"1","right":"1","bottom":"1","left":"1","isLinked":true},"image_border_color":"","name_size":"h4","image_margin_bottom":{"unit":"px","size":15,"sizes":[]},"desc_margin":{"unit":"px","size":22,"sizes":[]},"_margin":{"unit":"px","top":"10","right":"10","bottom":"10","left":"10","isLinked":true},"_padding":{"unit":"px","top":"15","right":"15","bottom":"15","left":"15","isLinked":true},"_background_background":"classic","_background_color":"#F2F5F7","shape":"circle","name_margin":{"unit":"px","size":10,"sizes":[]},"social_icons_settings":"yes","show_team_member_desig":"","image_shape":"square","image_border":"none","image_border_size":{"unit":"px","top":"1","right":"1","bottom":"1","left":"1","isLinked":true},"content_padding":{"unit":"px","top":"","right":"","bottom":"","left":"","isLinked":true},"separator_margin":{"unit":"px","size":"","sizes":[]},"_border_width":{"unit":"px","top":"","right":"","bottom":"","left":"","isLinked":true},"_border_border":"","show_team_member_desc":"yes"},
	

	"preset-4" : {"image_size":"full","member_image_size":{"unit":"px","size":100,"sizes":[]},"social_icons_border_radius":{"unit":"%","top":"","right":"","bottom":"","left":"","isLinked":true},"icon_size":{"unit":"px","size":14,"sizes":[]},"icon_bg_size":{"unit":"px","size":25,"sizes":[]},"icon_spacing":{"unit":"px","size":8,"sizes":[]},"separator_settings":"","separator_position":"below_desig","separator_size":{"unit":"%","size":10,"sizes":[]},"separator_thickness":{"unit":"px","size":1,"sizes":[]},"team_member_image_border_radius":{"unit":"%","top":"3","right":"3","bottom":"3","left":"3","isLinked":true},"image_border_color":"","name_size":"h4","image_margin_bottom":{"unit":"px","size":15,"sizes":[]},"desc_margin":{"unit":"px","size":21,"sizes":[]},"_margin":{"unit":"px","top":"10","right":"10","bottom":"10","left":"10","isLinked":true},"_padding":{"unit":"px","top":"20","right":"20","bottom":"20","left":"20","isLinked":true},"_background_background":"classic","member_image_height":{"unit":"px","size":100,"sizes":[]},"shape":"circle","image_shape":"circle","name_margin":{"unit":"px","size":10,"sizes":[]},"_border_border":"solid","_border_width":{"unit":"px","top":"3","right":"3","bottom":"3","left":"3","isLinked":true},"_border_color":"#E5E8E9","_border_radius":{"unit":"px","top":"5","right":"5","bottom":"5","left":"5","isLinked":true},"social_icons_settings":"yes","show_team_member_desig":"","image_border":"none","image_border_size":{"unit":"px","top":"1","right":"1","bottom":"1","left":"1","isLinked":true},"content_padding":{"unit":"px","top":"","right":"","bottom":"","left":"","isLinked":true},"separator_margin":{"unit":"px","size":"","sizes":[]},"_background_color":"","show_team_member_desc":"yes"},
	
	
	"preset-5" : {"member_image_size":{"unit":"px","size":120,"sizes":[]},"member_image_height":{"unit":"px","size":120,"sizes":[]},"separator_settings":"","shape":"circle","image_position":"left","member_mob_view":"tablet","content_padding":{"unit":"px","top":"0","right":"20","bottom":"0","left":"20","isLinked":false},"icon_size":{"unit":"px","size":14,"sizes":[]},"icon_bg_size":{"unit":"px","size":24,"sizes":[]},"icon_spacing":{"unit":"px","size":5,"sizes":[]},"_padding":{"unit":"px","top":"20","right":"20","bottom":"20","left":"20","isLinked":true},"_background_background":"classic","_background_color":"#F5F5F5","_margin":{"unit":"px","top":"15","right":"15","bottom":"15","left":"15","isLinked":true},"image_size":"large","member_image_valign":"middle","image_shape":"circle","name_size":"h4","desc_margin":{"unit":"px","size":18,"sizes":[]},"social_icons_settings":"yes","show_team_member_desig":"yes","separator_position":"below_desig","separator_thickness":{"unit":"px","size":1,"sizes":[]},"image_border":"none","image_border_size":{"unit":"px","top":"1","right":"1","bottom":"1","left":"1","isLinked":true},"image_border_color":"","image_margin_bottom":{"unit":"px","size":"","sizes":[]},"separator_size":{"unit":"%","size":20,"sizes":[]},"name_margin":{"unit":"px","size":"","sizes":[]},"separator_margin":{"unit":"px","size":"","sizes":[]},"_border_width":{"unit":"px","top":"","right":"","bottom":"","left":"","isLinked":true},"_border_border":"","show_team_member_desc":"yes"}
	
}